rnadvisor2_webserver/Home.py
rnadvisor2_webserver/__init__.py
rnadvisor2_webserver/app.py
rnadvisor2_webserver/bin/USalign
rnadvisor2_webserver/data/CASP_RNA/.DS_Store
rnadvisor2_webserver/data/CASP_RNA/NATIVE/.DS_Store
rnadvisor2_webserver/data/CASP_RNA/NATIVE/R1107.pdb
rnadvisor2_webserver/data/CASP_RNA/NATIVE/R1108.pdb
rnadvisor2_webserver/data/CASP_RNA/NATIVE/R1116.pdb
rnadvisor2_webserver/data/CASP_RNA/NATIVE/R1117.pdb
rnadvisor2_webserver/data/CASP_RNA/NATIVE/R1126.pdb
rnadvisor2_webserver/data/CASP_RNA/NATIVE/R1128.pdb
rnadvisor2_webserver/data/CASP_RNA/NATIVE/R1149.pdb
rnadvisor2_webserver/data/CASP_RNA/NATIVE/R1156.pdb
rnadvisor2_webserver/data/CASP_RNA/NATIVE/R1189.pdb
rnadvisor2_webserver/data/CASP_RNA/NATIVE/R1190.pdb
rnadvisor2_webserver/data/CASP_RNA/PREDS/.DS_Store
rnadvisor2_webserver/data/CASP_RNA/PREDS/R1107/.DS_Store
rnadvisor2_webserver/data/CASP_RNA/PREDS/R1107/3drna_r1107_1.pdb
rnadvisor2_webserver/data/CASP_RNA/PREDS/R1107/alphafold3_R1107_1.pdb
rnadvisor2_webserver/data/CASP_RNA/PREDS/R1107/best_R1107_1.pdb
rnadvisor2_webserver/data/CASP_RNA/PREDS/R1107/mcsym_r1107_1.pdb
rnadvisor2_webserver/data/CASP_RNA/PREDS/R1107/rhofold_r1107.pdb
rnadvisor2_webserver/data/CASP_RNA/PREDS/R1107/rnacomposer_r1107.pdb
rnadvisor2_webserver/data/CASP_RNA/PREDS/R1107/trrosettarna_r1107_1.pdb
rnadvisor2_webserver/data/CASP_RNA/PREDS/R1107/vfoldpipeline_r1107.pdb
rnadvisor2_webserver/data/CASP_RNA/PREDS/R1108/.DS_Store
rnadvisor2_webserver/data/CASP_RNA/PREDS/R1108/3drna_r1108_1.pdb
rnadvisor2_webserver/data/CASP_RNA/PREDS/R1108/alphafold3_R1108_1.pdb
rnadvisor2_webserver/data/CASP_RNA/PREDS/R1108/best_R1108_1.pdb
rnadvisor2_webserver/data/CASP_RNA/PREDS/R1108/rhofold_R1108.pdb
rnadvisor2_webserver/data/CASP_RNA/PREDS/R1108/rnacomposer_r1108.pdb
rnadvisor2_webserver/data/CASP_RNA/PREDS/R1108/trrosettarna_r1108_1.pdb
rnadvisor2_webserver/data/CASP_RNA/PREDS/R1108/vfoldpipeline_r1108.pdb
rnadvisor2_webserver/data/CASP_RNA/PREDS/R1116/.DS_Store
rnadvisor2_webserver-0.1.3.dist-info/METADATA
rnadvisor2_webserver-0.1.3.dist-info/WHEEL
rnadvisor2_webserver-0.1.3.dist-info/entry_points.txt
rnadvisor2_webserver-0.1.3.dist-info/top_level.txt
rnadvisor2_webserver-0.1.3.dist-info/RECORD
