Metadata-Version: 2.4
Name: rnadvisor2_webserver
Version: 0.1.3
Summary: RNAdvisor is a wrapper tool for the computation of RNA 3D structural quality assessment.
Requires-Python: >=3.10
Requires-Dist: plotly>=6.1.2
Requires-Dist: rnadvisor>=2.1.8
Requires-Dist: scikit-learn>=1.3.2
Requires-Dist: numpy>=1.24.4
Requires-Dist: streamlit>=1.46.0
Requires-Dist: streamlit-javascript>=0.1.5
Requires-Dist: streamlit-molstar>=0.4.21
Requires-Dist: torch>=2.7.1
Requires-Dist: transformers>=4.52.4
Requires-Dist: protobuf<5
